gql/__init__.py
gql/__version__.py
gql/cli.py
gql/client.py
gql/dsl.py
gql/gql.py
gql/graphql_request.py
gql/py.typed
gql/utils.py
gql/transport/__init__.py
gql/transport/aiohttp.py
gql/transport/appsync_auth.py
gql/transport/appsync_websockets.py
gql/transport/async_transport.py
gql/transport/exceptions.py
gql/transport/httpx.py
gql/transport/local_schema.py
gql/transport/phoenix_channel_websockets.py
gql/transport/requests.py
gql/transport/transport.py
gql/transport/websockets.py
gql/transport/websockets_base.py
gql/utilities/__init__.py
gql/utilities/build_client_schema.py
gql/utilities/get_introspection_query_ast.py
gql/utilities/node_tree.py
gql/utilities/parse_result.py
gql/utilities/serialize_variable_values.py
gql/utilities/update_schema_enum.py
gql/utilities/update_schema_scalars.py
gql-3.5.2.dist-info/LICENSE
gql-3.5.2.dist-info/METADATA
gql-3.5.2.dist-info/WHEEL
gql-3.5.2.dist-info/entry_points.txt
gql-3.5.2.dist-info/top_level.txt
gql-3.5.2.dist-info/RECORD
