Metadata-Version: 2.1
Name: gql
Version: 3.5.2
Summary: GraphQL client for Python
Home-page: https://github.com/graphql-python/gql
Author: Syrus Akbary
Author-email: me@syrusakbary.com
License: MIT
Keywords: api graphql protocol rest relay gql client
Platform: any
Classifier: Development Status :: 5 - Production/Stable
Classifier: Intended Audience :: Developers
Classifier: Topic :: Software Development :: Libraries
Classifier: Programming Language :: Python :: 3
Classifier: Programming Language :: Python :: 3 :: Only
Classifier: Programming Language :: Python :: 3.7
Classifier: Programming Language :: Python :: 3.8
Classifier: Programming Language :: Python :: 3.9
Classifier: Programming Language :: Python :: 3.10
Classifier: Programming Language :: Python :: 3.11
Classifier: Programming Language :: Python :: 3.12
Classifier: Programming Language :: Python :: Implementation :: PyPy
Provides-Extra: all
Provides-Extra: test
Provides-Extra: test_no_transport
Provides-Extra: dev
Provides-Extra: aiohttp
Provides-Extra: requests
Provides-Extra: httpx
Provides-Extra: websockets
Provides-Extra: botocore
